mpld3/__about__.py
mpld3/__init__.py
mpld3/_display.py
mpld3/_server.py
mpld3/mpld3renderer.py
mpld3/plugins.py
mpld3/urls.py
mpld3/utils.py
mpld3/js/d3.v3.min.js
mpld3/js/d3.v5.min.js
mpld3/js/mpld3.v0.3.1.dev1.js
mpld3/js/mpld3.v0.3.1.dev1.min.js
mpld3/js/mpld3.v0.4.0.js
mpld3/js/mpld3.v0.4.0.min.js
mpld3/js/mpld3.v0.4.1.js
mpld3/js/mpld3.v0.4.1.min.js
mpld3/js/mpld3.v0.4.12.js
mpld3/js/mpld3.v0.4.12.min.js
mpld3/js/mpld3.v0.4.2.js
mpld3/js/mpld3.v0.4.2.min.js
mpld3/mplexporter/__init__.py
mpld3/mplexporter/_py3k_compat.py
mpld3/mplexporter/convertors.py
mpld3/mplexporter/exporter.py
mpld3/mplexporter/tools.py
mpld3/mplexporter/utils.py
mpld3/mplexporter/renderers/__init__.py
mpld3/mplexporter/renderers/base.py
mpld3/mplexporter/renderers/fake_renderer.py
mpld3/mplexporter/renderers/vega_renderer.py
mpld3/mplexporter/renderers/vincent_renderer.py
mpld3_valuegrid-0.4.12.dist-info/AUTHORS.md
mpld3_valuegrid-0.4.12.dist-info/LICENSE
mpld3_valuegrid-0.4.12.dist-info/METADATA
mpld3_valuegrid-0.4.12.dist-info/WHEEL
mpld3_valuegrid-0.4.12.dist-info/top_level.txt
mpld3_valuegrid-0.4.12.dist-info/RECORD
